CHANGELOG.txt
LICENCE.txt
MANIFEST.in
README.txt
setup.py
yt2mp3down/__init__.py
yt2mp3down.egg-info/PKG-INFO
yt2mp3down.egg-info/SOURCES.txt
yt2mp3down.egg-info/dependency_links.txt
yt2mp3down.egg-info/top_level.txt
yt2mp3down/r/__init__.py
yt2mp3down/r/__version__.py
yt2mp3down/r/_internal_utils.py
yt2mp3down/r/adapters.py
yt2mp3down/r/api.py
yt2mp3down/r/auth.py
yt2mp3down/r/certs.py
yt2mp3down/r/compat.py
yt2mp3down/r/cookies.py
yt2mp3down/r/exceptions.py
yt2mp3down/r/help.py
yt2mp3down/r/hooks.py
yt2mp3down/r/models.py
yt2mp3down/r/packages.py
yt2mp3down/r/sessions.py
yt2mp3down/r/status_codes.py
yt2mp3down/r/structures.py
yt2mp3down/r/utils.py
yt2mp3down/t/__init__.py
yt2mp3down/t/__main__.py
yt2mp3down/t/_dist_ver.py
yt2mp3down/t/_main.py
yt2mp3down/t/_monitor.py
yt2mp3down/t/_tqdm.py
yt2mp3down/t/_tqdm_gui.py
yt2mp3down/t/_tqdm_notebook.py
yt2mp3down/t/_tqdm_pandas.py
yt2mp3down/t/_utils.py
yt2mp3down/t/asyncio.py
yt2mp3down/t/auto.py
yt2mp3down/t/autonotebook.py
yt2mp3down/t/cli.py
yt2mp3down/t/dask.py
yt2mp3down/t/gui.py
yt2mp3down/t/keras.py
yt2mp3down/t/notebook.py
yt2mp3down/t/rich.py
yt2mp3down/t/std.py
yt2mp3down/t/tk.py
yt2mp3down/t/utils.py
yt2mp3down/t/version.py
yt2mp3down/t/contrib/__init__.py
yt2mp3down/t/contrib/bells.py
yt2mp3down/t/contrib/concurrent.py
yt2mp3down/t/contrib/discord.py
yt2mp3down/t/contrib/itertools.py
yt2mp3down/t/contrib/telegram.py
yt2mp3down/t/contrib/utils_worker.py