Metadata-Version: 1.1
Name: yt2mp3down
Version: 0.0.1
Summary: A very basic calculator
Home-page: UNKNOWN
Author: Hasinthaka Piyumal
Author-email: hasinthakapiyumal@gmail.com
License: MIT
Keywords: yt2mp3
Platform: UNKNOWN
Classifier: Development Status :: 5 - Production/Stable
Classifier: Intended Audience :: Education
Classifier: Operating System :: Microsoft :: Windows :: Windows 10
Classifier: License :: OSI Approved :: MIT License
Classifier: Programming Language :: Python :: 3
